{
  "name": "room_forest_afterthrash2",
  "width": 1520,
  "height": 480,
  "canvasWidth": 1570,
  "canvasHeight": 520,
  "canvasOffsetX": 40,
  "canvasOffsetY": 40,
  "speed": 0,
  "persistent": false,
  "backgroundColor": "#000000",
  "drawBackgroundColor": false,
  "isGMS2": true,
  "isGMS2_3": true,
  "enableViews": true,
  "gridWidth": 40,
  "gridHeight": 40,
  "layers": [
    {
      "name": "Compatibility_Colour",
      "type": "Background",
      "depth": 2147483600,
      "layerId": 758,
      "visible": true,
      "xOffset": 0,
      "yOffset": 0,
      "hSpeed": 0,
      "vSpeed": 0,
      "backgroundData": {
        "sprite": null,
        "visible": true,
        "foreground": false,
        "stretch": false,
        "tiledHorizontally": false,
        "tiledVertically": false,
        "color": "#000000",
        "firstFrame": 0,
        "animationSpeed": 15,
        "animationSpeedType": "FPS"
      }
    },
    {
      "name": "Compatibility_Tiles_Depth_1000000",
      "type": "Assets",
      "depth": 1000000,
      "layerId": 757,
      "visible": true,
      "xOffset": 0,
      "yOffset": 0,
      "hSpeed": 0,
      "vSpeed": 0,
      "assetsData": {
        "legacyTiles": [
          {
            "x": 0,
            "y": 200,
            "width": 40,
            "height": 40,
            "sourceX": 40,
            "sourceY": 120,
            "sprite": "bg_darkforest_tiles",
            "instanceID": 10023385,
            "tileDepth": 1000000,
            "scaleX": 1,
            "scaleY": 1,
            "color": "#FFFFFF"
          },
          {
            "x": 40,
            "y": 200,
            "width": 40,
            "height": 40,
            "sourceX": 40,
            "sourceY": 120,
            "sprite": "bg_darkforest_tiles",
            "instanceID": 10023386,
            "tileDepth": 1000000,
            "scaleX": 1,
            "scaleY": 1,
            "color": "#FFFFFF"
          },
          {
            "x": 80,
            "y": 200,
            "width": 40,
            "height": 40,
            "sourceX": 40,
            "sourceY": 120,
            "sprite": "bg_darkforest_tiles",
            "instanceID": 10023387,
            "tileDepth": 1000000,
            "scaleX": 1,
            "scaleY": 1,
            "color": "#FFFFFF"
          },
          {
            "x": 120,
            "y": 200,
            "width": 40,
            "height": 40,
            "sourceX": 40,
            "sourceY": 120,
            "sprite": "bg_darkforest_tiles",
            "instanceID": 10023388,
            "tileDepth": 1000000,
            "scaleX": 1,
            "scaleY": 1,
            "color": "#FFFFFF"
          },
          {
            "x": 160,
            "y": 200,
            "width": 40,
            "height": 40,
            "sourceX": 40,
            "sourceY": 120,
            "sprite": "bg_darkforest_tiles",
            "instanceID": 10023389,
            "tileDepth": 1000000,
            "scaleX": 1,
            "scaleY": 1,
            "color": "#FFFFFF"
          },
          {
            "x": 200,
            "y": 200,
            "width": 40,
            "height": 40,
            "sourceX": 40,
            "sourceY": 120,
            "sprite": "bg_darkforest_tiles",
            "instanceID": 10023390,
            "tileDepth": 1000000,
            "scaleX": 1,
            "scaleY": 1,
            "color": "#FFFFFF"
          },
          {
            "x": 280,
            "y": 240,
            "width": 40,
            "height": 40,
            "sourceX": 40,
            "sourceY": 120,
            "sprite": "bg_darkforest_tiles",
            "instanceID": 10023391,
            "tileDepth": 1000000,
            "scaleX": 1,
            "scaleY": 1,
            "color": "#FFFFFF"
          },
          {
            "x": 320,
            "y": 240,
            "width": 40,
            "height": 40,
            "sourceX": 40,
            "sourceY": 120,
            "sprite": "bg_darkforest_tiles",
            "instanceID": 10023392,
            "tileDepth": 1000000,
            "scaleX": 1,
            "scaleY": 1,
            "color": "#FFFFFF"
          },
          {
            "x": 360,
            "y": 240,
            "width": 40,
            "height": 40,
            "sourceX": 40,
            "sourceY": 120,
            "sprite": "bg_darkforest_tiles",
            "instanceID": 10023393,
            "tileDepth": 1000000,
            "scaleX": 1,
            "scaleY": 1,
            "color": "#FFFFFF"
          },
          {
            "x": 400,
            "y": 240,
            "width": 40,
            "height": 40,
            "sourceX": 40,
            "sourceY": 120,
            "sprite": "bg_darkforest_tiles",
            "instanceID": 10023394,
            "tileDepth": 1000000,
            "scaleX": 1,
            "scaleY": 1,
            "color": "#FFFFFF"
          },
          {
            "x": 480,
            "y": 200,
            "width": 40,
            "height": 40,
            "sourceX": 40,
            "sourceY": 120,
            "sprite": "bg_darkforest_tiles",
            "instanceID": 10023395,
            "tileDepth": 1000000,
            "scaleX": 1,
            "scaleY": 1,
            "color": "#FFFFFF"
          },
          {
            "x": 520,
            "y": 200,
            "width": 40,
            "height": 40,
            "sourceX": 40,
            "sourceY": 120,
            "sprite": "bg_darkforest_tiles",
            "instanceID": 10023396,
            "tileDepth": 1000000,
            "scaleX": 1,
            "scaleY": 1,
            "color": "#FFFFFF"
          },
          {
            "x": 560,
            "y": 200,
            "width": 40,
            "height": 40,
            "sourceX": 40,
            "sourceY": 120,
            "sprite": "bg_darkforest_tiles",
            "instanceID": 10023397,
            "tileDepth": 1000000,
            "scaleX": 1,
            "scaleY": 1,
            "color": "#FFFFFF"
          },
          {
            "x": 600,
            "y": 200,
            "width": 40,
            "height": 40,
            "sourceX": 40,
            "sourceY": 120,
            "sprite": "bg_darkforest_tiles",
            "instanceID": 10023398,
            "tileDepth": 1000000,
            "scaleX": 1,
            "scaleY": 1,
            "color": "#FFFFFF"
          },
          {
            "x": 640,
            "y": 200,
            "width": 40,
            "height": 40,
            "sourceX": 40,
            "sourceY": 120,
            "sprite": "bg_darkforest_tiles",
            "instanceID": 10023399,
            "tileDepth": 1000000,
            "scaleX": 1,
            "scaleY": 1,
            "color": "#FFFFFF"
          },
          {
            "x": 680,
            "y": 200,
            "width": 40,
            "height": 40,
            "sourceX": 40,
            "sourceY": 120,
            "sprite": "bg_darkforest_tiles",
            "instanceID": 10023400,
            "tileDepth": 1000000,
            "scaleX": 1,
            "scaleY": 1,
            "color": "#FFFFFF"
          },
          {
            "x": 760,
            "y": 240,
            "width": 40,
            "height": 40,
            "sourceX": 40,
            "sourceY": 120,
            "sprite": "bg_darkforest_tiles",
            "instanceID": 10023401,
            "tileDepth": 1000000,
            "scaleX": 1,
            "scaleY": 1,
            "color": "#FFFFFF"
          },
          {
            "x": 800,
            "y": 240,
            "width": 40,
            "height": 40,
            "sourceX": 40,
            "sourceY": 120,
            "sprite": "bg_darkforest_tiles",
            "instanceID": 10023402,
            "tileDepth": 1000000,
            "scaleX": 1,
            "scaleY": 1,
            "color": "#FFFFFF"
          },
          {
            "x": 840,
            "y": 240,
            "width": 40,
            "height": 40,
            "sourceX": 40,
            "sourceY": 120,
            "sprite": "bg_darkforest_tiles",
            "instanceID": 10023403,
            "tileDepth": 1000000,
            "scaleX": 1,
            "scaleY": 1,
            "color": "#FFFFFF"
          },
          {
            "x": 880,
            "y": 240,
            "width": 40,
            "height": 40,
            "sourceX": 40,
            "sourceY": 120,
            "sprite": "bg_darkforest_tiles",
            "instanceID": 10023404,
            "tileDepth": 1000000,
            "scaleX": 1,
            "scaleY": 1,
            "color": "#FFFFFF"
          },
          {
            "x": 960,
            "y": 200,
            "width": 40,
            "height": 40,
            "sourceX": 40,
            "sourceY": 120,
            "sprite": "bg_darkforest_tiles",
            "instanceID": 10023405,
            "tileDepth": 1000000,
            "scaleX": 1,
            "scaleY": 1,
            "color": "#FFFFFF"
          },
          {
            "x": 1000,
            "y": 200,
            "width": 40,
            "height": 40,
            "sourceX": 40,
            "sourceY": 120,
            "sprite": "bg_darkforest_tiles",
            "instanceID": 10023406,
            "tileDepth": 1000000,
            "scaleX": 1,
            "scaleY": 1,
            "color": "#FFFFFF"
          },
          {
            "x": 1040,
            "y": 200,
            "width": 40,
            "height": 40,
            "sourceX": 40,
            "sourceY": 120,
            "sprite": "bg_darkforest_tiles",
            "instanceID": 10023407,
            "tileDepth": 1000000,
            "scaleX": 1,
            "scaleY": 1,
            "color": "#FFFFFF"
          },
          {
            "x": 1080,
            "y": 200,
            "width": 40,
            "height": 40,
            "sourceX": 40,
            "sourceY": 120,
            "sprite": "bg_darkforest_tiles",
            "instanceID": 10023408,
            "tileDepth": 1000000,
            "scaleX": 1,
            "scaleY": 1,
            "color": "#FFFFFF"
          },
          {
            "x": 1120,
            "y": 200,
            "width": 40,
            "height": 40,
            "sourceX": 40,
            "sourceY": 120,
            "sprite": "bg_darkforest_tiles",
            "instanceID": 10023409,
            "tileDepth": 1000000,
            "scaleX": 1,
            "scaleY": 1,
            "color": "#FFFFFF"
          },
          {
            "x": 1160,
            "y": 200,
            "width": 40,
            "height": 40,
            "sourceX": 40,
            "sourceY": 120,
            "sprite": "bg_darkforest_tiles",
            "instanceID": 10023410,
            "tileDepth": 1000000,
            "scaleX": 1,
            "scaleY": 1,
            "color": "#FFFFFF"
          },
          {
            "x": 1200,
            "y": 200,
            "width": 40,
            "height": 40,
            "sourceX": 40,
            "sourceY": 120,
            "sprite": "bg_darkforest_tiles",
            "instanceID": 10023411,
            "tileDepth": 1000000,
            "scaleX": 1,
            "scaleY": 1,
            "color": "#FFFFFF"
          },
          {
            "x": 1240,
            "y": 200,
            "width": 40,
            "height": 40,
            "sourceX": 40,
            "sourceY": 120,
            "sprite": "bg_darkforest_tiles",
            "instanceID": 10023412,
            "tileDepth": 1000000,
            "scaleX": 1,
            "scaleY": 1,
            "color": "#FFFFFF"
          },
          {
            "x": 1280,
            "y": 200,
            "width": 40,
            "height": 40,
            "sourceX": 40,
            "sourceY": 120,
            "sprite": "bg_darkforest_tiles",
            "instanceID": 10023413,
            "tileDepth": 1000000,
            "scaleX": 1,
            "scaleY": 1,
            "color": "#FFFFFF"
          },
          {
            "x": 1320,
            "y": 200,
            "width": 40,
            "height": 40,
            "sourceX": 40,
            "sourceY": 120,
            "sprite": "bg_darkforest_tiles",
            "instanceID": 10023414,
            "tileDepth": 1000000,
            "scaleX": 1,
            "scaleY": 1,
            "color": "#FFFFFF"
          },
          {
            "x": 1360,
            "y": 200,
            "width": 40,
            "height": 40,
            "sourceX": 40,
            "sourceY": 120,
            "sprite": "bg_darkforest_tiles",
            "instanceID": 10023415,
            "tileDepth": 1000000,
            "scaleX": 1,
            "scaleY": 1,
            "color": "#FFFFFF"
          },
          {
            "x": 1400,
            "y": 200,
            "width": 40,
            "height": 40,
            "sourceX": 40,
            "sourceY": 120,
            "sprite": "bg_darkforest_tiles",
            "instanceID": 10023416,
            "tileDepth": 1000000,
            "scaleX": 1,
            "scaleY": 1,
            "color": "#FFFFFF"
          },
          {
            "x": 1440,
            "y": 200,
            "width": 40,
            "height": 40,
            "sourceX": 40,
            "sourceY": 120,
            "sprite": "bg_darkforest_tiles",
            "instanceID": 10023417,
            "tileDepth": 1000000,
            "scaleX": 1,
            "scaleY": 1,
            "color": "#FFFFFF"
          },
          {
            "x": 1480,
            "y": 200,
            "width": 40,
            "height": 40,
            "sourceX": 40,
            "sourceY": 120,
            "sprite": "bg_darkforest_tiles",
            "instanceID": 10023418,
            "tileDepth": 1000000,
            "scaleX": 1,
            "scaleY": 1,
            "color": "#FFFFFF"
          },
          {
            "x": 0,
            "y": 240,
            "width": 40,
            "height": 40,
            "sourceX": 40,
            "sourceY": 200,
            "sprite": "bg_darkforest_tiles",
            "instanceID": 10023419,
            "tileDepth": 1000000,
            "scaleX": 1,
            "scaleY": 1,
            "color": "#FFFFFF"
          },
          {
            "x": 40,
            "y": 240,
            "width": 40,
            "height": 40,
            "sourceX": 40,
            "sourceY": 200,
            "sprite": "bg_darkforest_tiles",
            "instanceID": 10023420,
            "tileDepth": 1000000,
            "scaleX": 1,
            "scaleY": 1,
            "color": "#FFFFFF"
          },
          {
            "x": 80,
            "y": 240,
            "width": 40,
            "height": 40,
            "sourceX": 40,
            "sourceY": 200,
            "sprite": "bg_darkforest_tiles",
            "instanceID": 10023421,
            "tileDepth": 1000000,
            "scaleX": 1,
            "scaleY": 1,
            "color": "#FFFFFF"
          },
          {
            "x": 120,
            "y": 240,
            "width": 40,
            "height": 40,
            "sourceX": 40,
            "sourceY": 200,
            "sprite": "bg_darkforest_tiles",
            "instanceID": 10023422,
            "tileDepth": 1000000,
            "scaleX": 1,
            "scaleY": 1,
            "color": "#FFFFFF"
          },
          {
            "x": 160,
            "y": 240,
            "width": 40,
            "height": 40,
            "sourceX": 40,
            "sourceY": 200,
            "sprite": "bg_darkforest_tiles",
            "instanceID": 10023423,
            "tileDepth": 1000000,
            "scaleX": 1,
            "scaleY": 1,
            "color": "#FFFFFF"
          },
          {
            "x": 240,
            "y": 280,
            "width": 40,
            "height": 40,
            "sourceX": 40,
            "sourceY": 200,
            "sprite": "bg_darkforest_tiles",
            "instanceID": 10023424,
            "tileDepth": 1000000,
            "scaleX": 1,
            "scaleY": 1,
            "color": "#FFFFFF"
          },
          {
            "x": 280,
            "y": 280,
            "width": 40,
            "height": 40,
            "sourceX": 40,
            "sourceY": 200,
            "sprite": "bg_darkforest_tiles",
            "instanceID": 10023425,
            "tileDepth": 1000000,
            "scaleX": 1,
            "scaleY": 1,
            "color": "#FFFFFF"
          },
          {
            "x": 320,
            "y": 280,
            "width": 40,
            "height": 40,
            "sourceX": 40,
            "sourceY": 200,
            "sprite": "bg_darkforest_tiles",
            "instanceID": 10023426,
            "tileDepth": 1000000,
            "scaleX": 1,
            "scaleY": 1,
            "color": "#FFFFFF"
          },
          {
            "x": 360,
            "y": 280,
            "width": 40,
            "height": 40,
            "sourceX": 40,
            "sourceY": 200,
            "sprite": "bg_darkforest_tiles",
            "instanceID": 10023427,
            "tileDepth": 1000000,
            "scaleX": 1,
            "scaleY": 1,
            "color": "#FFFFFF"
          },
          {
            "x": 400,
            "y": 280,
            "width": 40,
            "height": 40,
            "sourceX": 40,
            "sourceY": 200,
            "sprite": "bg_darkforest_tiles",
            "instanceID": 10023428,
            "tileDepth": 1000000,
            "scaleX": 1,
            "scaleY": 1,
            "color": "#FFFFFF"
          },
          {
            "x": 440,
            "y": 280,
            "width": 40,
            "height": 40,
            "sourceX": 40,
            "sourceY": 200,
            "sprite": "bg_darkforest_tiles",
            "instanceID": 10023429,
            "tileDepth": 1000000,
            "scaleX": 1,
            "scaleY": 1,
            "color": "#FFFFFF"
          },
          {
            "x": 520,
            "y": 240,
            "width": 40,
            "height": 40,
            "sourceX": 40,
            "sourceY": 200,
            "sprite": "bg_darkforest_tiles",
            "instanceID": 10023430,
            "tileDepth": 1000000,
            "scaleX": 1,
            "scaleY": 1,
            "color": "#FFFFFF"
          },
          {
            "x": 560,
            "y": 240,
            "width": 40,
            "height": 40,
            "sourceX": 40,
            "sourceY": 200,
            "sprite": "bg_darkforest_tiles",
            "instanceID": 10023431,
            "tileDepth": 1000000,
            "scaleX": 1,
            "scaleY": 1,
            "color": "#FFFFFF"
          },
          {
            "x": 600,
            "y": 240,
            "width": 40,
            "height": 40,
            "sourceX": 40,
            "sourceY": 200,
            "sprite": "bg_darkforest_tiles",
            "instanceID": 10023432,
            "tileDepth": 1000000,
            "scaleX": 1,
            "scaleY": 1,
            "color": "#FFFFFF"
          },
          {
            "x": 640,
            "y": 240,
            "width": 40,
            "height": 40,
            "sourceX": 40,
            "sourceY": 200,
            "sprite": "bg_darkforest_tiles",
            "instanceID": 10023433,
            "tileDepth": 1000000,
            "scaleX": 1,
            "scaleY": 1,
            "color": "#FFFFFF"
          },
          {
            "x": 720,
            "y": 280,
            "width": 40,
            "height": 40,
            "sourceX": 40,
            "sourceY": 200,
            "sprite": "bg_darkforest_tiles",
            "instanceID": 10023434,
            "tileDepth": 1000000,
            "scaleX": 1,
            "scaleY": 1,
            "color": "#FFFFFF"
          },
          {
            "x": 760,
            "y": 280,
            "width": 40,
            "height": 40,
            "sourceX": 40,
            "sourceY": 200,
            "sprite": "bg_darkforest_tiles",
            "instanceID": 10023435,
            "tileDepth": 1000000,
            "scaleX": 1,
            "scaleY": 1,
            "color": "#FFFFFF"
          },
          {
            "x": 800,
            "y": 280,
            "width": 40,
            "height": 40,
            "sourceX": 40,
            "sourceY": 200,
            "sprite": "bg_darkforest_tiles",
            "instanceID": 10023436,
            "tileDepth": 1000000,
            "scaleX": 1,
            "scaleY": 1,
            "color": "#FFFFFF"
          },
          {
            "x": 840,
            "y": 280,
            "width": 40,
            "height": 40,
            "sourceX": 40,
            "sourceY": 200,
            "sprite": "bg_darkforest_tiles",
            "instanceID": 10023437,
            "tileDepth": 1000000,
            "scaleX": 1,
            "scaleY": 1,
            "color": "#FFFFFF"
          },
          {
            "x": 880,
            "y": 280,
            "width": 40,
            "height": 40,
            "sourceX": 40,
            "sourceY": 200,
            "sprite": "bg_darkforest_tiles",
            "instanceID": 10023438,
            "tileDepth": 1000000,
            "scaleX": 1,
            "scaleY": 1,
            "color": "#FFFFFF"
          },
          {
            "x": 920,
            "y": 280,
            "width": 40,
            "height": 40,
            "sourceX": 40,
            "sourceY": 200,
            "sprite": "bg_darkforest_tiles",
            "instanceID": 10023439,
            "tileDepth": 1000000,
            "scaleX": 1,
            "scaleY": 1,
            "color": "#FFFFFF"
          },
          {
            "x": 960,
            "y": 280,
            "width": 40,
            "height": 40,
            "sourceX": 40,
            "sourceY": 200,
            "sprite": "bg_darkforest_tiles",
            "instanceID": 10023440,
            "tileDepth": 1000000,
            "scaleX": 1,
            "scaleY": 1,
            "color": "#FFFFFF"
          },
          {
            "x": 1000,
            "y": 280,
            "width": 40,
            "height": 40,
            "sourceX": 40,
            "sourceY": 200,
            "sprite": "bg_darkforest_tiles",
            "instanceID": 10023441,
            "tileDepth": 1000000,
            "scaleX": 1,
            "scaleY": 1,
            "color": "#FFFFFF"
          },
          {
            "x": 1040,
            "y": 280,
            "width": 40,
            "height": 40,
            "sourceX": 40,
            "sourceY": 200,
            "sprite": "bg_darkforest_tiles",
            "instanceID": 10023442,
            "tileDepth": 1000000,
            "scaleX": 1,
            "scaleY": 1,
            "color": "#FFFFFF"
          },
          {
            "x": 1120,
            "y": 240,
            "width": 40,
            "height": 40,
            "sourceX": 40,
            "sourceY": 200,
            "sprite": "bg_darkforest_tiles",
            "instanceID": 10023443,
            "tileDepth": 1000000,
            "scaleX": 1,
            "scaleY": 1,
            "color": "#FFFFFF"
          },
          {
            "x": 1160,
            "y": 240,
            "width": 40,
            "height": 40,
            "sourceX": 40,
            "sourceY": 200,
            "sprite": "bg_darkforest_tiles",
            "instanceID": 10023444,
            "tileDepth": 1000000,
            "scaleX": 1,
            "scaleY": 1,
            "color": "#FFFFFF"
          },
          {
            "x": 1200,
            "y": 240,
            "width": 40,
            "height": 40,
            "sourceX": 40,
            "sourceY": 200,
            "sprite": "bg_darkforest_tiles",
            "instanceID": 10023445,
            "tileDepth": 1000000,
            "scaleX": 1,
            "scaleY": 1,
            "color": "#FFFFFF"
          },
          {
            "x": 1240,
            "y": 240,
            "width": 40,
            "height": 40,
            "sourceX": 40,
            "sourceY": 200,
            "sprite": "bg_darkforest_tiles",
            "instanceID": 10023446,
            "tileDepth": 1000000,
            "scaleX": 1,
            "scaleY": 1,
            "color": "#FFFFFF"
          },
          {
            "x": 1280,
            "y": 240,
            "width": 40,
            "height": 40,
            "sourceX": 40,
            "sourceY": 200,
            "sprite": "bg_darkforest_tiles",
            "instanceID": 10023447,
            "tileDepth": 1000000,
            "scaleX": 1,
            "scaleY": 1,
            "color": "#FFFFFF"
          },
          {
            "x": 1320,
            "y": 240,
            "width": 40,
            "height": 40,
            "sourceX": 40,
            "sourceY": 200,
            "sprite": "bg_darkforest_tiles",
            "instanceID": 10023448,
            "tileDepth": 1000000,
            "scaleX": 1,
            "scaleY": 1,
            "color": "#FFFFFF"
          },
          {
            "x": 1360,
            "y": 240,
            "width": 40,
            "height": 40,
            "sourceX": 40,
            "sourceY": 200,
            "sprite": "bg_darkforest_tiles",
            "instanceID": 10023449,
            "tileDepth": 1000000,
            "scaleX": 1,
            "scaleY": 1,
            "color": "#FFFFFF"
          },
          {
            "x": 1400,
            "y": 240,
            "width": 40,
            "height": 40,
            "sourceX": 40,
            "sourceY": 200,
            "sprite": "bg_darkforest_tiles",
            "instanceID": 10023450,
            "tileDepth": 1000000,
            "scaleX": 1,
            "scaleY": 1,
            "color": "#FFFFFF"
          },
          {
            "x": 1440,
            "y": 240,
            "width": 40,
            "height": 40,
            "sourceX": 40,
            "sourceY": 200,
            "sprite": "bg_darkforest_tiles",
            "instanceID": 10023451,
            "tileDepth": 1000000,
            "scaleX": 1,
            "scaleY": 1,
            "color": "#FFFFFF"
          },
          {
            "x": 1480,
            "y": 240,
            "width": 40,
            "height": 40,
            "sourceX": 40,
            "sourceY": 200,
            "sprite": "bg_darkforest_tiles",
            "instanceID": 10023452,
            "tileDepth": 1000000,
            "scaleX": 1,
            "scaleY": 1,
            "color": "#FFFFFF"
          },
          {
            "x": 1080,
            "y": 280,
            "width": 40,
            "height": 40,
            "sourceX": 80,
            "sourceY": 200,
            "sprite": "bg_darkforest_tiles",
            "instanceID": 10023453,
            "tileDepth": 1000000,
            "scaleX": 1,
            "scaleY": 1,
            "color": "#FFFFFF"
          },
          {
            "x": 480,
            "y": 280,
            "width": 40,
            "height": 40,
            "sourceX": 80,
            "sourceY": 200,
            "sprite": "bg_darkforest_tiles",
            "instanceID": 10023454,
            "tileDepth": 1000000,
            "scaleX": 1,
            "scaleY": 1,
            "color": "#FFFFFF"
          },
          {
            "x": 200,
            "y": 280,
            "width": 40,
            "height": 40,
            "sourceX": 0,
            "sourceY": 200,
            "sprite": "bg_darkforest_tiles",
            "instanceID": 10023455,
            "tileDepth": 1000000,
            "scaleX": 1,
            "scaleY": 1,
            "color": "#FFFFFF"
          },
          {
            "x": 680,
            "y": 280,
            "width": 40,
            "height": 40,
            "sourceX": 0,
            "sourceY": 200,
            "sprite": "bg_darkforest_tiles",
            "instanceID": 10023456,
            "tileDepth": 1000000,
            "scaleX": 1,
            "scaleY": 1,
            "color": "#FFFFFF"
          },
          {
            "x": 240,
            "y": 200,
            "width": 40,
            "height": 40,
            "sourceX": 80,
            "sourceY": 120,
            "sprite": "bg_darkforest_tiles",
            "instanceID": 10023457,
            "tileDepth": 1000000,
            "scaleX": 1,
            "scaleY": 1,
            "color": "#FFFFFF"
          },
          {
            "x": 720,
            "y": 200,
            "width": 40,
            "height": 40,
            "sourceX": 80,
            "sourceY": 120,
            "sprite": "bg_darkforest_tiles",
            "instanceID": 10023458,
            "tileDepth": 1000000,
            "scaleX": 1,
            "scaleY": 1,
            "color": "#FFFFFF"
          },
          {
            "x": 440,
            "y": 200,
            "width": 40,
            "height": 40,
            "sourceX": 0,
            "sourceY": 120,
            "sprite": "bg_darkforest_tiles",
            "instanceID": 10023459,
            "tileDepth": 1000000,
            "scaleX": 1,
            "scaleY": 1,
            "color": "#FFFFFF"
          },
          {
            "x": 920,
            "y": 200,
            "width": 40,
            "height": 40,
            "sourceX": 0,
            "sourceY": 120,
            "sprite": "bg_darkforest_tiles",
            "instanceID": 10023460,
            "tileDepth": 1000000,
            "scaleX": 1,
            "scaleY": 1,
            "color": "#FFFFFF"
          },
          {
            "x": 200,
            "y": 240,
            "width": 40,
            "height": 40,
            "sourceX": 40,
            "sourceY": 160,
            "sprite": "bg_darkforest_tiles",
            "instanceID": 10023461,
            "tileDepth": 1000000,
            "scaleX": 1,
            "scaleY": 1,
            "color": "#FFFFFF"
          },
          {
            "x": 240,
            "y": 240,
            "width": 40,
            "height": 40,
            "sourceX": 40,
            "sourceY": 160,
            "sprite": "bg_darkforest_tiles",
            "instanceID": 10023462,
            "tileDepth": 1000000,
            "scaleX": 1,
            "scaleY": 1,
            "color": "#FFFFFF"
          },
          {
            "x": 440,
            "y": 240,
            "width": 40,
            "height": 40,
            "sourceX": 40,
            "sourceY": 160,
            "sprite": "bg_darkforest_tiles",
            "instanceID": 10023463,
            "tileDepth": 1000000,
            "scaleX": 1,
            "scaleY": 1,
            "color": "#FFFFFF"
          },
          {
            "x": 480,
            "y": 240,
            "width": 40,
            "height": 40,
            "sourceX": 40,
            "sourceY": 160,
            "sprite": "bg_darkforest_tiles",
            "instanceID": 10023464,
            "tileDepth": 1000000,
            "scaleX": 1,
            "scaleY": 1,
            "color": "#FFFFFF"
          },
          {
            "x": 680,
            "y": 240,
            "width": 40,
            "height": 40,
            "sourceX": 40,
            "sourceY": 160,
            "sprite": "bg_darkforest_tiles",
            "instanceID": 10023465,
            "tileDepth": 1000000,
            "scaleX": 1,
            "scaleY": 1,
            "color": "#FFFFFF"
          },
          {
            "x": 720,
            "y": 240,
            "width": 40,
            "height": 40,
            "sourceX": 40,
            "sourceY": 160,
            "sprite": "bg_darkforest_tiles",
            "instanceID": 10023466,
            "tileDepth": 1000000,
            "scaleX": 1,
            "scaleY": 1,
            "color": "#FFFFFF"
          },
          {
            "x": 920,
            "y": 240,
            "width": 40,
            "height": 40,
            "sourceX": 40,
            "sourceY": 160,
            "sprite": "bg_darkforest_tiles",
            "instanceID": 10023467,
            "tileDepth": 1000000,
            "scaleX": 1,
            "scaleY": 1,
            "color": "#FFFFFF"
          },
          {
            "x": 960,
            "y": 240,
            "width": 40,
            "height": 40,
            "sourceX": 40,
            "sourceY": 160,
            "sprite": "bg_darkforest_tiles",
            "instanceID": 10023468,
            "tileDepth": 1000000,
            "scaleX": 1,
            "scaleY": 1,
            "color": "#FFFFFF"
          },
          {
            "x": 1000,
            "y": 240,
            "width": 40,
            "height": 40,
            "sourceX": 40,
            "sourceY": 160,
            "sprite": "bg_darkforest_tiles",
            "instanceID": 10023469,
            "tileDepth": 1000000,
            "scaleX": 1,
            "scaleY": 1,
            "color": "#FFFFFF"
          },
          {
            "x": 1040,
            "y": 240,
            "width": 40,
            "height": 40,
            "sourceX": 40,
            "sourceY": 160,
            "sprite": "bg_darkforest_tiles",
            "instanceID": 10023470,
            "tileDepth": 1000000,
            "scaleX": 1,
            "scaleY": 1,
            "color": "#FFFFFF"
          },
          {
            "x": 1080,
            "y": 240,
            "width": 40,
            "height": 40,
            "sourceX": 40,
            "sourceY": 160,
            "sprite": "bg_darkforest_tiles",
            "instanceID": 10023471,
            "tileDepth": 1000000,
            "scaleX": 1,
            "scaleY": 1,
            "color": "#FFFFFF"
          },
          {
            "x": 0,
            "y": 400,
            "width": 80,
            "height": 80,
            "sourceX": 40,
            "sourceY": 280,
            "sprite": "bg_darkforest_tiles",
            "instanceID": 10023472,
            "tileDepth": 1000000,
            "scaleX": 1,
            "scaleY": 1,
            "color": "#FFFFFF"
          },
          {
            "x": 80,
            "y": 400,
            "width": 80,
            "height": 80,
            "sourceX": 40,
            "sourceY": 280,
            "sprite": "bg_darkforest_tiles",
            "instanceID": 10023473,
            "tileDepth": 1000000,
            "scaleX": 1,
            "scaleY": 1,
            "color": "#FFFFFF"
          },
          {
            "x": 160,
            "y": 400,
            "width": 80,
            "height": 80,
            "sourceX": 40,
            "sourceY": 280,
            "sprite": "bg_darkforest_tiles",
            "instanceID": 10023474,
            "tileDepth": 1000000,
            "scaleX": 1,
            "scaleY": 1,
            "color": "#FFFFFF"
          },
          {
            "x": 240,
            "y": 400,
            "width": 80,
            "height": 80,
            "sourceX": 40,
            "sourceY": 280,
            "sprite": "bg_darkforest_tiles",
            "instanceID": 10023475,
            "tileDepth": 1000000,
            "scaleX": 1,
            "scaleY": 1,
            "color": "#FFFFFF"
          },
          {
            "x": 320,
            "y": 400,
            "width": 80,
            "height": 80,
            "sourceX": 40,
            "sourceY": 280,
            "sprite": "bg_darkforest_tiles",
            "instanceID": 10023476,
            "tileDepth": 1000000,
            "scaleX": 1,
            "scaleY": 1,
            "color": "#FFFFFF"
          },
          {
            "x": 400,
            "y": 400,
            "width": 80,
            "height": 80,
            "sourceX": 40,
            "sourceY": 280,
            "sprite": "bg_darkforest_tiles",
            "instanceID": 10023477,
            "tileDepth": 1000000,
            "scaleX": 1,
            "scaleY": 1,
            "color": "#FFFFFF"
          },
          {
            "x": 480,
            "y": 400,
            "width": 80,
            "height": 80,
            "sourceX": 40,
            "sourceY": 280,
            "sprite": "bg_darkforest_tiles",
            "instanceID": 10023478,
            "tileDepth": 1000000,
            "scaleX": 1,
            "scaleY": 1,
            "color": "#FFFFFF"
          },
          {
            "x": 560,
            "y": 400,
            "width": 80,
            "height": 80,
            "sourceX": 40,
            "sourceY": 280,
            "sprite": "bg_darkforest_tiles",
            "instanceID": 10023479,
            "tileDepth": 1000000,
            "scaleX": 1,
            "scaleY": 1,
            "color": "#FFFFFF"
          },
          {
            "x": 640,
            "y": 400,
            "width": 80,
            "height": 80,
            "sourceX": 40,
            "sourceY": 280,
            "sprite": "bg_darkforest_tiles",
            "instanceID": 10023480,
            "tileDepth": 1000000,
            "scaleX": 1,
            "scaleY": 1,
            "color": "#FFFFFF"
          },
          {
            "x": 720,
            "y": 400,
            "width": 80,
            "height": 80,
            "sourceX": 40,
            "sourceY": 280,
            "sprite": "bg_darkforest_tiles",
            "instanceID": 10023481,
            "tileDepth": 1000000,
            "scaleX": 1,
            "scaleY": 1,
            "color": "#FFFFFF"
          },
          {
            "x": 800,
            "y": 400,
            "width": 80,
            "height": 80,
            "sourceX": 40,
            "sourceY": 280,
            "sprite": "bg_darkforest_tiles",
            "instanceID": 10023482,
            "tileDepth": 1000000,
            "scaleX": 1,
            "scaleY": 1,
            "color": "#FFFFFF"
          },
          {
            "x": 880,
            "y": 400,
            "width": 80,
            "height": 80,
            "sourceX": 40,
            "sourceY": 280,
            "sprite": "bg_darkforest_tiles",
            "instanceID": 10023483,
            "tileDepth": 1000000,
            "scaleX": 1,
            "scaleY": 1,
            "color": "#FFFFFF"
          },
          {
            "x": 960,
            "y": 400,
            "width": 80,
            "height": 80,
            "sourceX": 40,
            "sourceY": 280,
            "sprite": "bg_darkforest_tiles",
            "instanceID": 10023484,
            "tileDepth": 1000000,
            "scaleX": 1,
            "scaleY": 1,
            "color": "#FFFFFF"
          },
          {
            "x": 1040,
            "y": 400,
            "width": 80,
            "height": 80,
            "sourceX": 40,
            "sourceY": 280,
            "sprite": "bg_darkforest_tiles",
            "instanceID": 10023485,
            "tileDepth": 1000000,
            "scaleX": 1,
            "scaleY": 1,
            "color": "#FFFFFF"
          },
          {
            "x": 1120,
            "y": 400,
            "width": 80,
            "height": 80,
            "sourceX": 40,
            "sourceY": 280,
            "sprite": "bg_darkforest_tiles",
            "instanceID": 10023486,
            "tileDepth": 1000000,
            "scaleX": 1,
            "scaleY": 1,
            "color": "#FFFFFF"
          },
          {
            "x": 1200,
            "y": 400,
            "width": 80,
            "height": 80,
            "sourceX": 40,
            "sourceY": 280,
            "sprite": "bg_darkforest_tiles",
            "instanceID": 10023487,
            "tileDepth": 1000000,
            "scaleX": 1,
            "scaleY": 1,
            "color": "#FFFFFF"
          },
          {
            "x": 1280,
            "y": 400,
            "width": 80,
            "height": 80,
            "sourceX": 40,
            "sourceY": 280,
            "sprite": "bg_darkforest_tiles",
            "instanceID": 10023488,
            "tileDepth": 1000000,
            "scaleX": 1,
            "scaleY": 1,
            "color": "#FFFFFF"
          },
          {
            "x": 1360,
            "y": 400,
            "width": 80,
            "height": 80,
            "sourceX": 40,
            "sourceY": 280,
            "sprite": "bg_darkforest_tiles",
            "instanceID": 10023489,
            "tileDepth": 1000000,
            "scaleX": 1,
            "scaleY": 1,
            "color": "#FFFFFF"
          },
          {
            "x": 1440,
            "y": 400,
            "width": 80,
            "height": 80,
            "sourceX": 40,
            "sourceY": 280,
            "sprite": "bg_darkforest_tiles",
            "instanceID": 10023490,
            "tileDepth": 1000000,
            "scaleX": 1,
            "scaleY": 1,
            "color": "#FFFFFF"
          },
          {
            "x": 0,
            "y": 360,
            "width": 80,
            "height": 40,
            "sourceX": 40,
            "sourceY": 240,
            "sprite": "bg_darkforest_tiles",
            "instanceID": 10023491,
            "tileDepth": 1000000,
            "scaleX": 1,
            "scaleY": 1,
            "color": "#FFFFFF"
          },
          {
            "x": 80,
            "y": 360,
            "width": 80,
            "height": 40,
            "sourceX": 40,
            "sourceY": 240,
            "sprite": "bg_darkforest_tiles",
            "instanceID": 10023492,
            "tileDepth": 1000000,
            "scaleX": 1,
            "scaleY": 1,
            "color": "#FFFFFF"
          },
          {
            "x": 160,
            "y": 360,
            "width": 80,
            "height": 40,
            "sourceX": 40,
            "sourceY": 240,
            "sprite": "bg_darkforest_tiles",
            "instanceID": 10023493,
            "tileDepth": 1000000,
            "scaleX": 1,
            "scaleY": 1,
            "color": "#FFFFFF"
          },
          {
            "x": 240,
            "y": 360,
            "width": 80,
            "height": 40,
            "sourceX": 40,
            "sourceY": 240,
            "sprite": "bg_darkforest_tiles",
            "instanceID": 10023494,
            "tileDepth": 1000000,
            "scaleX": 1,
            "scaleY": 1,
            "color": "#FFFFFF"
          },
          {
            "x": 320,
            "y": 360,
            "width": 80,
            "height": 40,
            "sourceX": 40,
            "sourceY": 240,
            "sprite": "bg_darkforest_tiles",
            "instanceID": 10023495,
            "tileDepth": 1000000,
            "scaleX": 1,
            "scaleY": 1,
            "color": "#FFFFFF"
          },
          {
            "x": 400,
            "y": 360,
            "width": 80,
            "height": 40,
            "sourceX": 40,
            "sourceY": 240,
            "sprite": "bg_darkforest_tiles",
            "instanceID": 10023496,
            "tileDepth": 1000000,
            "scaleX": 1,
            "scaleY": 1,
            "color": "#FFFFFF"
          },
          {
            "x": 480,
            "y": 360,
            "width": 80,
            "height": 40,
            "sourceX": 40,
            "sourceY": 240,
            "sprite": "bg_darkforest_tiles",
            "instanceID": 10023497,
            "tileDepth": 1000000,
            "scaleX": 1,
            "scaleY": 1,
            "color": "#FFFFFF"
          },
          {
            "x": 560,
            "y": 360,
            "width": 80,
            "height": 40,
            "sourceX": 40,
            "sourceY": 240,
            "sprite": "bg_darkforest_tiles",
            "instanceID": 10023498,
            "tileDepth": 1000000,
            "scaleX": 1,
            "scaleY": 1,
            "color": "#FFFFFF"
          },
          {
            "x": 640,
            "y": 360,
            "width": 80,
            "height": 40,
            "sourceX": 40,
            "sourceY": 240,
            "sprite": "bg_darkforest_tiles",
            "instanceID": 10023499,
            "tileDepth": 1000000,
            "scaleX": 1,
            "scaleY": 1,
            "color": "#FFFFFF"
          },
          {
            "x": 720,
            "y": 360,
            "width": 80,
            "height": 40,
            "sourceX": 40,
            "sourceY": 240,
            "sprite": "bg_darkforest_tiles",
            "instanceID": 10023500,
            "tileDepth": 1000000,
            "scaleX": 1,
            "scaleY": 1,
            "color": "#FFFFFF"
          },
          {
            "x": 800,
            "y": 360,
            "width": 80,
            "height": 40,
            "sourceX": 40,
            "sourceY": 240,
            "sprite": "bg_darkforest_tiles",
            "instanceID": 10023501,
            "tileDepth": 1000000,
            "scaleX": 1,
            "scaleY": 1,
            "color": "#FFFFFF"
          },
          {
            "x": 880,
            "y": 360,
            "width": 80,
            "height": 40,
            "sourceX": 40,
            "sourceY": 240,
            "sprite": "bg_darkforest_tiles",
            "instanceID": 10023502,
            "tileDepth": 1000000,
            "scaleX": 1,
            "scaleY": 1,
            "color": "#FFFFFF"
          },
          {
            "x": 960,
            "y": 360,
            "width": 80,
            "height": 40,
            "sourceX": 40,
            "sourceY": 240,
            "sprite": "bg_darkforest_tiles",
            "instanceID": 10023503,
            "tileDepth": 1000000,
            "scaleX": 1,
            "scaleY": 1,
            "color": "#FFFFFF"
          },
          {
            "x": 1040,
            "y": 360,
            "width": 80,
            "height": 40,
            "sourceX": 40,
            "sourceY": 240,
            "sprite": "bg_darkforest_tiles",
            "instanceID": 10023504,
            "tileDepth": 1000000,
            "scaleX": 1,
            "scaleY": 1,
            "color": "#FFFFFF"
          },
          {
            "x": 1120,
            "y": 360,
            "width": 80,
            "height": 40,
            "sourceX": 40,
            "sourceY": 240,
            "sprite": "bg_darkforest_tiles",
            "instanceID": 10023505,
            "tileDepth": 1000000,
            "scaleX": 1,
            "scaleY": 1,
            "color": "#FFFFFF"
          },
          {
            "x": 1200,
            "y": 360,
            "width": 80,
            "height": 40,
            "sourceX": 40,
            "sourceY": 240,
            "sprite": "bg_darkforest_tiles",
            "instanceID": 10023506,
            "tileDepth": 1000000,
            "scaleX": 1,
            "scaleY": 1,
            "color": "#FFFFFF"
          },
          {
            "x": 1280,
            "y": 360,
            "width": 80,
            "height": 40,
            "sourceX": 40,
            "sourceY": 240,
            "sprite": "bg_darkforest_tiles",
            "instanceID": 10023507,
            "tileDepth": 1000000,
            "scaleX": 1,
            "scaleY": 1,
            "color": "#FFFFFF"
          },
          {
            "x": 1360,
            "y": 360,
            "width": 80,
            "height": 40,
            "sourceX": 40,
            "sourceY": 240,
            "sprite": "bg_darkforest_tiles",
            "instanceID": 10023508,
            "tileDepth": 1000000,
            "scaleX": 1,
            "scaleY": 1,
            "color": "#FFFFFF"
          },
          {
            "x": 1440,
            "y": 360,
            "width": 80,
            "height": 40,
            "sourceX": 40,
            "sourceY": 240,
            "sprite": "bg_darkforest_tiles",
            "instanceID": 10023509,
            "tileDepth": 1000000,
            "scaleX": 1,
            "scaleY": 1,
            "color": "#FFFFFF"
          },
          {
            "x": 0,
            "y": -40,
            "width": 80,
            "height": 160,
            "sourceX": 40,
            "sourceY": 280,
            "sprite": "bg_darkforest_tiles",
            "instanceID": 10023510,
            "tileDepth": 1000000,
            "scaleX": 1,
            "scaleY": 1,
            "color": "#FFFFFF"
          },
          {
            "x": 80,
            "y": -40,
            "width": 80,
            "height": 160,
            "sourceX": 40,
            "sourceY": 280,
            "sprite": "bg_darkforest_tiles",
            "instanceID": 10023511,
            "tileDepth": 1000000,
            "scaleX": 1,
            "scaleY": 1,
            "color": "#FFFFFF"
          },
          {
            "x": 160,
            "y": -40,
            "width": 80,
            "height": 160,
            "sourceX": 40,
            "sourceY": 280,
            "sprite": "bg_darkforest_tiles",
            "instanceID": 10023512,
            "tileDepth": 1000000,
            "scaleX": 1,
            "scaleY": 1,
            "color": "#FFFFFF"
          },
          {
            "x": 240,
            "y": -40,
            "width": 80,
            "height": 160,
            "sourceX": 40,
            "sourceY": 280,
            "sprite": "bg_darkforest_tiles",
            "instanceID": 10023513,
            "tileDepth": 1000000,
            "scaleX": 1,
            "scaleY": 1,
            "color": "#FFFFFF"
          },
          {
            "x": 320,
            "y": -40,
            "width": 80,
            "height": 160,
            "sourceX": 40,
            "sourceY": 280,
            "sprite": "bg_darkforest_tiles",
            "instanceID": 10023514,
            "tileDepth": 1000000,
            "scaleX": 1,
            "scaleY": 1,
            "color": "#FFFFFF"
          },
          {
            "x": 400,
            "y": -40,
            "width": 80,
            "height": 160,
            "sourceX": 40,
            "sourceY": 280,
            "sprite": "bg_darkforest_tiles",
            "instanceID": 10023515,
            "tileDepth": 1000000,
            "scaleX": 1,
            "scaleY": 1,
            "color": "#FFFFFF"
          },
          {
            "x": 480,
            "y": -40,
            "width": 80,
            "height": 160,
            "sourceX": 40,
            "sourceY": 280,
            "sprite": "bg_darkforest_tiles",
            "instanceID": 10023516,
            "tileDepth": 1000000,
            "scaleX": 1,
            "scaleY": 1,
            "color": "#FFFFFF"
          },
          {
            "x": 560,
            "y": -40,
            "width": 80,
            "height": 160,
            "sourceX": 40,
            "sourceY": 280,
            "sprite": "bg_darkforest_tiles",
            "instanceID": 10023517,
            "tileDepth": 1000000,
            "scaleX": 1,
            "scaleY": 1,
            "color": "#FFFFFF"
          },
          {
            "x": 640,
            "y": -40,
            "width": 80,
            "height": 160,
            "sourceX": 40,
            "sourceY": 280,
            "sprite": "bg_darkforest_tiles",
            "instanceID": 10023518,
            "tileDepth": 1000000,
            "scaleX": 1,
            "scaleY": 1,
            "color": "#FFFFFF"
          },
          {
            "x": 720,
            "y": -40,
            "width": 80,
            "height": 160,
            "sourceX": 40,
            "sourceY": 280,
            "sprite": "bg_darkforest_tiles",
            "instanceID": 10023519,
            "tileDepth": 1000000,
            "scaleX": 1,
            "scaleY": 1,
            "color": "#FFFFFF"
          },
          {
            "x": 800,
            "y": -40,
            "width": 80,
            "height": 160,
            "sourceX": 40,
            "sourceY": 280,
            "sprite": "bg_darkforest_tiles",
            "instanceID": 10023520,
            "tileDepth": 1000000,
            "scaleX": 1,
            "scaleY": 1,
            "color": "#FFFFFF"
          },
          {
            "x": 880,
            "y": -40,
            "width": 80,
            "height": 160,
            "sourceX": 40,
            "sourceY": 280,
            "sprite": "bg_darkforest_tiles",
            "instanceID": 10023521,
            "tileDepth": 1000000,
            "scaleX": 1,
            "scaleY": 1,
            "color": "#FFFFFF"
          },
          {
            "x": 960,
            "y": -40,
            "width": 80,
            "height": 160,
            "sourceX": 40,
            "sourceY": 280,
            "sprite": "bg_darkforest_tiles",
            "instanceID": 10023522,
            "tileDepth": 1000000,
            "scaleX": 1,
            "scaleY": 1,
            "color": "#FFFFFF"
          },
          {
            "x": 1040,
            "y": -40,
            "width": 80,
            "height": 160,
            "sourceX": 40,
            "sourceY": 280,
            "sprite": "bg_darkforest_tiles",
            "instanceID": 10023523,
            "tileDepth": 1000000,
            "scaleX": 1,
            "scaleY": 1,
            "color": "#FFFFFF"
          },
          {
            "x": 1120,
            "y": -40,
            "width": 80,
            "height": 160,
            "sourceX": 40,
            "sourceY": 280,
            "sprite": "bg_darkforest_tiles",
            "instanceID": 10023524,
            "tileDepth": 1000000,
            "scaleX": 1,
            "scaleY": 1,
            "color": "#FFFFFF"
          },
          {
            "x": 1200,
            "y": -40,
            "width": 80,
            "height": 160,
            "sourceX": 40,
            "sourceY": 280,
            "sprite": "bg_darkforest_tiles",
            "instanceID": 10023525,
            "tileDepth": 1000000,
            "scaleX": 1,
            "scaleY": 1,
            "color": "#FFFFFF"
          },
          {
            "x": 1280,
            "y": -40,
            "width": 80,
            "height": 160,
            "sourceX": 40,
            "sourceY": 280,
            "sprite": "bg_darkforest_tiles",
            "instanceID": 10023526,
            "tileDepth": 1000000,
            "scaleX": 1,
            "scaleY": 1,
            "color": "#FFFFFF"
          },
          {
            "x": 1360,
            "y": -40,
            "width": 80,
            "height": 160,
            "sourceX": 40,
            "sourceY": 280,
            "sprite": "bg_darkforest_tiles",
            "instanceID": 10023527,
            "tileDepth": 1000000,
            "scaleX": 1,
            "scaleY": 1,
            "color": "#FFFFFF"
          },
          {
            "x": 1440,
            "y": -40,
            "width": 80,
            "height": 160,
            "sourceX": 40,
            "sourceY": 280,
            "sprite": "bg_darkforest_tiles",
            "instanceID": 10023528,
            "tileDepth": 1000000,
            "scaleX": 1,
            "scaleY": 1,
            "color": "#FFFFFF"
          },
          {
            "x": 0,
            "y": 320,
            "width": 80,
            "height": 80,
            "sourceX": 40,
            "sourceY": 280,
            "sprite": "bg_darkforest_tiles",
            "instanceID": 10023529,
            "tileDepth": 1000000,
            "scaleX": 1,
            "scaleY": 1,
            "color": "#FFFFFF"
          },
          {
            "x": -40,
            "y": 280,
            "width": 120,
            "height": 40,
            "sourceX": 0,
            "sourceY": 240,
            "sprite": "bg_darkforest_tiles",
            "instanceID": 10023530,
            "tileDepth": 1000000,
            "scaleX": 1,
            "scaleY": 1,
            "color": "#FFFFFF"
          },
          {
            "x": 80,
            "y": 280,
            "width": 40,
            "height": 120,
            "sourceX": 120,
            "sourceY": 240,
            "sprite": "bg_darkforest_tiles",
            "instanceID": 10023531,
            "tileDepth": 1000000,
            "scaleX": 1,
            "scaleY": 1,
            "color": "#FFFFFF"
          }
        ]
      }
    },
    {
      "name": "Compatibility_Instances_Depth_950000",
      "type": "Instances",
      "depth": 950000,
      "layerId": 756,
      "visible": true,
      "xOffset": 0,
      "yOffset": 0,
      "hSpeed": 0,
      "vSpeed": 0,
      "instances": [
        {
          "x": 280,
          "y": 40,
          "objectName": "obj_musicer_bird",
          "instanceID": 102666,
          "scaleX": 1,
          "scaleY": 1,
          "rotation": 0,
          "color": "#FFFFFF"
        }
      ]
    },
    {
      "name": "Compatibility_Instances_Depth_800000",
      "type": "Instances",
      "depth": 800000,
      "layerId": 755,
      "visible": true,
      "xOffset": 0,
      "yOffset": 0,
      "hSpeed": 0,
      "vSpeed": 0,
      "instances": [
        {
          "x": 120,
          "y": 0,
          "objectName": "obj_blocktree_bg",
          "instanceID": 102664,
          "scaleX": 2,
          "scaleY": 2,
          "rotation": 0,
          "color": "#FFFFFF"
        },
        {
          "x": 740,
          "y": 30,
          "objectName": "obj_blocktree_bg",
          "instanceID": 102665,
          "scaleX": 2,
          "scaleY": 2,
          "rotation": 0,
          "color": "#FFFFFF"
        }
      ]
    },
    {
      "name": "Compatibility_Instances_Depth_500000",
      "type": "Instances",
      "depth": 500000,
      "layerId": 754,
      "visible": true,
      "xOffset": 0,
      "yOffset": 0,
      "hSpeed": 0,
      "vSpeed": 0,
      "instances": [
        {
          "x": 40,
          "y": 80,
          "objectName": "obj_thrashafter_follow",
          "instanceID": 102663,
          "scaleX": 2,
          "scaleY": 2,
          "rotation": 0,
          "color": "#FFFFFF"
        }
      ]
    },
    {
      "name": "Compatibility_Tiles_Depth_400000",
      "type": "Assets",
      "depth": 400000,
      "layerId": 753,
      "visible": true,
      "xOffset": 0,
      "yOffset": 0,
      "hSpeed": 0,
      "vSpeed": 0,
      "assetsData": {
        "legacyTiles": [
          {
            "x": 0,
            "y": 0,
            "width": 80,
            "height": 160,
            "sourceX": 80,
            "sourceY": 280,
            "sprite": "bg_darkforest_tiles",
            "instanceID": 10023384,
            "tileDepth": 400000,
            "scaleX": 1,
            "scaleY": 1,
            "color": "#FFFFFF"
          }
        ]
      }
    },
    {
      "name": "Compatibility_Instances_Depth_100",
      "type": "Instances",
      "depth": 100,
      "layerId": 752,
      "visible": true,
      "xOffset": 0,
      "yOffset": 0,
      "hSpeed": 0,
      "vSpeed": 0,
      "instances": [
        {
          "x": 0,
          "y": 160,
          "objectName": "obj_soliddark",
          "instanceID": 102653,
          "scaleX": 7,
          "scaleY": 1,
          "rotation": 0,
          "color": "#FFFFFF"
        },
        {
          "x": 280,
          "y": 200,
          "objectName": "obj_soliddark",
          "instanceID": 102654,
          "scaleX": 4,
          "scaleY": 1,
          "rotation": 0,
          "color": "#FFFFFF"
        },
        {
          "x": 0,
          "y": 280,
          "objectName": "obj_soliddark",
          "instanceID": 102655,
          "scaleX": 5,
          "scaleY": 1,
          "rotation": 0,
          "color": "#FFFFFF"
        },
        {
          "x": 200,
          "y": 320,
          "objectName": "obj_soliddark",
          "instanceID": 102656,
          "scaleX": 8,
          "scaleY": 1,
          "rotation": 0,
          "color": "#FFFFFF"
        },
        {
          "x": 440,
          "y": 160,
          "objectName": "obj_soliddark",
          "instanceID": 102657,
          "scaleX": 8,
          "scaleY": 1,
          "rotation": 0,
          "color": "#FFFFFF"
        },
        {
          "x": 520,
          "y": 280,
          "objectName": "obj_soliddark",
          "instanceID": 102658,
          "scaleX": 4,
          "scaleY": 1,
          "rotation": 0,
          "color": "#FFFFFF"
        },
        {
          "x": 680,
          "y": 320,
          "objectName": "obj_soliddark",
          "instanceID": 102659,
          "scaleX": 11,
          "scaleY": 1,
          "rotation": 0,
          "color": "#FFFFFF"
        },
        {
          "x": 1120,
          "y": 280,
          "objectName": "obj_soliddark",
          "instanceID": 102660,
          "scaleX": 10.25641,
          "scaleY": 1,
          "rotation": 0,
          "color": "#FFFFFF"
        },
        {
          "x": 760,
          "y": 200,
          "objectName": "obj_soliddark",
          "instanceID": 102661,
          "scaleX": 4,
          "scaleY": 1,
          "rotation": 0,
          "color": "#FFFFFF"
        },
        {
          "x": 920,
          "y": 160,
          "objectName": "obj_soliddark",
          "instanceID": 102662,
          "scaleX": 15,
          "scaleY": 1,
          "rotation": 0,
          "color": "#FFFFFF"
        }
      ]
    },
    {
      "name": "Compatibility_Instances_Depth_0",
      "type": "Instances",
      "depth": 0,
      "layerId": 751,
      "visible": true,
      "xOffset": 0,
      "yOffset": 0,
      "hSpeed": 0,
      "vSpeed": 0,
      "instances": [
        {
          "x": 0,
          "y": 0,
          "objectName": "obj_darkcontroller",
          "instanceID": 102647,
          "scaleX": 1,
          "scaleY": 1,
          "rotation": 0,
          "color": "#FFFFFF"
        },
        {
          "x": 0,
          "y": 200,
          "objectName": "obj_doorB",
          "instanceID": 102648,
          "scaleX": 2,
          "scaleY": 4,
          "rotation": 0,
          "color": "#FFFFFF"
        },
        {
          "x": 40,
          "y": 200,
          "objectName": "obj_markerA",
          "instanceID": 102649,
          "scaleX": 1,
          "scaleY": 1,
          "rotation": 0,
          "color": "#FFFFFF"
        },
        {
          "x": 1440,
          "y": 200,
          "objectName": "obj_markerB",
          "instanceID": 102650,
          "scaleX": 1,
          "scaleY": 1,
          "rotation": 0,
          "color": "#FFFFFF"
        },
        {
          "x": 1480,
          "y": 200,
          "objectName": "obj_doorA",
          "instanceID": 102651,
          "scaleX": 2,
          "scaleY": 4,
          "rotation": 0,
          "color": "#FFFFFF"
        },
        {
          "x": 40,
          "y": 200,
          "objectName": "obj_markerX",
          "instanceID": 102652,
          "scaleX": 1,
          "scaleY": 1,
          "rotation": 0,
          "color": "#FFFFFF"
        }
      ]
    },
    {
      "name": "Compatibility_Instances_Depth_-20",
      "type": "Instances",
      "depth": -20,
      "layerId": 750,
      "visible": true,
      "xOffset": 0,
      "yOffset": 0,
      "hSpeed": 0,
      "vSpeed": 0,
      "instances": [
        {
          "x": 40,
          "y": 200,
          "objectName": "obj_mainchara",
          "instanceID": 102646,
          "scaleX": 2,
          "scaleY": 2,
          "rotation": 0,
          "color": "#FFFFFF"
        }
      ]
    }
  ],
  "gameObjects": [
    {
      "x": 40,
      "y": 200,
      "objectName": "obj_mainchara",
      "instanceID": 102646,
      "scaleX": 2,
      "scaleY": 2,
      "rotation": 0,
      "color": "#FFFFFF"
    },
    {
      "x": 0,
      "y": 0,
      "objectName": "obj_darkcontroller",
      "instanceID": 102647,
      "scaleX": 1,
      "scaleY": 1,
      "rotation": 0,
      "color": "#FFFFFF"
    },
    {
      "x": 0,
      "y": 200,
      "objectName": "obj_doorB",
      "instanceID": 102648,
      "scaleX": 2,
      "scaleY": 4,
      "rotation": 0,
      "color": "#FFFFFF"
    },
    {
      "x": 40,
      "y": 200,
      "objectName": "obj_markerA",
      "instanceID": 102649,
      "scaleX": 1,
      "scaleY": 1,
      "rotation": 0,
      "color": "#FFFFFF"
    },
    {
      "x": 1440,
      "y": 200,
      "objectName": "obj_markerB",
      "instanceID": 102650,
      "scaleX": 1,
      "scaleY": 1,
      "rotation": 0,
      "color": "#FFFFFF"
    },
    {
      "x": 1480,
      "y": 200,
      "objectName": "obj_doorA",
      "instanceID": 102651,
      "scaleX": 2,
      "scaleY": 4,
      "rotation": 0,
      "color": "#FFFFFF"
    },
    {
      "x": 0,
      "y": 160,
      "objectName": "obj_soliddark",
      "instanceID": 102653,
      "scaleX": 7,
      "scaleY": 1,
      "rotation": 0,
      "color": "#FFFFFF"
    },
    {
      "x": 280,
      "y": 200,
      "objectName": "obj_soliddark",
      "instanceID": 102654,
      "scaleX": 4,
      "scaleY": 1,
      "rotation": 0,
      "color": "#FFFFFF"
    },
    {
      "x": 0,
      "y": 280,
      "objectName": "obj_soliddark",
      "instanceID": 102655,
      "scaleX": 5,
      "scaleY": 1,
      "rotation": 0,
      "color": "#FFFFFF"
    },
    {
      "x": 200,
      "y": 320,
      "objectName": "obj_soliddark",
      "instanceID": 102656,
      "scaleX": 8,
      "scaleY": 1,
      "rotation": 0,
      "color": "#FFFFFF"
    },
    {
      "x": 440,
      "y": 160,
      "objectName": "obj_soliddark",
      "instanceID": 102657,
      "scaleX": 8,
      "scaleY": 1,
      "rotation": 0,
      "color": "#FFFFFF"
    },
    {
      "x": 520,
      "y": 280,
      "objectName": "obj_soliddark",
      "instanceID": 102658,
      "scaleX": 4,
      "scaleY": 1,
      "rotation": 0,
      "color": "#FFFFFF"
    },
    {
      "x": 680,
      "y": 320,
      "objectName": "obj_soliddark",
      "instanceID": 102659,
      "scaleX": 11,
      "scaleY": 1,
      "rotation": 0,
      "color": "#FFFFFF"
    },
    {
      "x": 1120,
      "y": 280,
      "objectName": "obj_soliddark",
      "instanceID": 102660,
      "scaleX": 10.25641,
      "scaleY": 1,
      "rotation": 0,
      "color": "#FFFFFF"
    },
    {
      "x": 760,
      "y": 200,
      "objectName": "obj_soliddark",
      "instanceID": 102661,
      "scaleX": 4,
      "scaleY": 1,
      "rotation": 0,
      "color": "#FFFFFF"
    },
    {
      "x": 920,
      "y": 160,
      "objectName": "obj_soliddark",
      "instanceID": 102662,
      "scaleX": 15,
      "scaleY": 1,
      "rotation": 0,
      "color": "#FFFFFF"
    },
    {
      "x": 40,
      "y": 80,
      "objectName": "obj_thrashafter_follow",
      "instanceID": 102663,
      "scaleX": 2,
      "scaleY": 2,
      "rotation": 0,
      "color": "#FFFFFF"
    },
    {
      "x": 40,
      "y": 200,
      "objectName": "obj_markerX",
      "instanceID": 102652,
      "scaleX": 1,
      "scaleY": 1,
      "rotation": 0,
      "color": "#FFFFFF"
    },
    {
      "x": 280,
      "y": 40,
      "objectName": "obj_musicer_bird",
      "instanceID": 102666,
      "scaleX": 1,
      "scaleY": 1,
      "rotation": 0,
      "color": "#FFFFFF"
    },
    {
      "x": 120,
      "y": 0,
      "objectName": "obj_blocktree_bg",
      "instanceID": 102664,
      "scaleX": 2,
      "scaleY": 2,
      "rotation": 0,
      "color": "#FFFFFF"
    },
    {
      "x": 740,
      "y": 30,
      "objectName": "obj_blocktree_bg",
      "instanceID": 102665,
      "scaleX": 2,
      "scaleY": 2,
      "rotation": 0,
      "color": "#FFFFFF"
    }
  ],
  "views": [
    {
      "enabled": true,
      "viewX": 0,
      "viewY": 0,
      "viewWidth": 640,
      "viewHeight": 480,
      "portX": 0,
      "portY": 0,
      "portWidth": 640,
      "portHeight": 480,
      "borderX": 160,
      "borderY": 240,
      "speedX": -1,
      "speedY": -1,
      "followsObject": null
    },
    {
      "enabled": false,
      "viewX": 0,
      "viewY": 0,
      "viewWidth": 1024,
      "viewHeight": 768,
      "portX": 0,
      "portY": 0,
      "portWidth": 1024,
      "portHeight": 768,
      "borderX": 32,
      "borderY": 32,
      "speedX": -1,
      "speedY": -1,
      "followsObject": null
    },
    {
      "enabled": false,
      "viewX": 0,
      "viewY": 0,
      "viewWidth": 1024,
      "viewHeight": 768,
      "portX": 0,
      "portY": 0,
      "portWidth": 1024,
      "portHeight": 768,
      "borderX": 32,
      "borderY": 32,
      "speedX": -1,
      "speedY": -1,
      "followsObject": null
    },
    {
      "enabled": false,
      "viewX": 0,
      "viewY": 0,
      "viewWidth": 1024,
      "viewHeight": 768,
      "portX": 0,
      "portY": 0,
      "portWidth": 1024,
      "portHeight": 768,
      "borderX": 32,
      "borderY": 32,
      "speedX": -1,
      "speedY": -1,
      "followsObject": null
    },
    {
      "enabled": false,
      "viewX": 0,
      "viewY": 0,
      "viewWidth": 1024,
      "viewHeight": 768,
      "portX": 0,
      "portY": 0,
      "portWidth": 1024,
      "portHeight": 768,
      "borderX": 32,
      "borderY": 32,
      "speedX": -1,
      "speedY": -1,
      "followsObject": null
    },
    {
      "enabled": false,
      "viewX": 0,
      "viewY": 0,
      "viewWidth": 1024,
      "viewHeight": 768,
      "portX": 0,
      "portY": 0,
      "portWidth": 1024,
      "portHeight": 768,
      "borderX": 32,
      "borderY": 32,
      "speedX": -1,
      "speedY": -1,
      "followsObject": null
    },
    {
      "enabled": false,
      "viewX": 0,
      "viewY": 0,
      "viewWidth": 1024,
      "viewHeight": 768,
      "portX": 0,
      "portY": 0,
      "portWidth": 1024,
      "portHeight": 768,
      "borderX": 32,
      "borderY": 32,
      "speedX": -1,
      "speedY": -1,
      "followsObject": null
    },
    {
      "enabled": false,
      "viewX": 0,
      "viewY": 0,
      "viewWidth": 1024,
      "viewHeight": 768,
      "portX": 0,
      "portY": 0,
      "portWidth": 1024,
      "portHeight": 768,
      "borderX": 32,
      "borderY": 32,
      "speedX": -1,
      "speedY": -1,
      "followsObject": null
    }
  ]
}